{
	"files": {
		"proto/all_test.go": {
			"status": "M",
			"num_chunks": 1,
			"no_base_file": false,
			"property_changes": "",
			"num_added": 75,
			"num_removed": 0,
			"id": 2,
			"is_binary": false
		},
		"proto/decode.go": {
			"status": "M",
			"num_chunks": 2,
			"no_base_file": false,
			"property_changes": "",
			"num_added": 3,
			"num_removed": 2,
			"id": 3,
			"is_binary": false
		},
		"proto/encode.go": {
			"status": "M",
			"num_chunks": 1,
			"no_base_file": false,
			"property_changes": "",
			"num_added": 4,
			"num_removed": 4,
			"id": 4,
			"is_binary": false
		}
	},
	"url": null,
	"created": "2010-11-28 02:01:35.746753",
	"owner": "mkrautz",
	"num_comments": 16,
	"patchset": 1,
	"owner_email": "krautz@gmail.com",
	"issue": 3274043,
	"message": null,
	"modified": "2010-11-29 00:09:16.171352"
}