{
	"files": {
		"src/cmd/gc/go.h": {
			"status": "M",
			"num_chunks": 4,
			"no_base_file": false,
			"property_changes": "",
			"num_added": 12,
			"num_removed": 0,
			"id": 22002,
			"is_binary": false
		},
		"src/cmd/gc/lex.c": {
			"status": "M",
			"num_chunks": 1,
			"no_base_file": false,
			"property_changes": "",
			"num_added": 15,
			"num_removed": 0,
			"id": 22004,
			"is_binary": false
		},
		"src/cmd/gc/Makefile": {
			"status": "M",
			"num_chunks": 1,
			"no_base_file": false,
			"property_changes": "",
			"num_added": 1,
			"num_removed": 0,
			"id": 22001,
			"is_binary": false
		},
		"src/cmd/gc/walk.c": {
			"status": "M",
			"num_chunks": 2,
			"no_base_file": false,
			"property_changes": "",
			"num_added": 3,
			"num_removed": 3,
			"id": 22005,
			"is_binary": false
		},
		"src/cmd/gc/inl.c": {
			"status": "A",
			"num_chunks": 1,
			"no_base_file": false,
			"property_changes": "",
			"num_added": 395,
			"num_removed": 0,
			"id": 22003,
			"is_binary": false
		}
	},
	"url": null,
	"created": "2011-08-12 12:20:22.256017",
	"owner": "lvd",
	"num_comments": 0,
	"patchset": 21001,
	"owner_email": "lvd@google.com",
	"issue": 4849051,
	"message": "diff -r 1edd4df99360 https://go.googlecode.com/hg/",
	"modified": "2011-08-12 12:20:22.256256"
}