{
	"files": {
		"salsa20/salsa20.go": {
			"status": "M",
			"num_chunks": 2,
			"no_base_file": false,
			"property_changes": "",
			"num_added": 4,
			"num_removed": 4,
			"id": 11001,
			"is_binary": false
		}
	},
	"url": null,
	"created": "2013-07-16 23:36:34.174640",
	"owner": "agl1",
	"num_comments": 0,
	"patchset": 10001,
	"owner_email": "agl@golang.org",
	"issue": 11033044,
	"message": "diff -r e6ec41d36ff8 https://code.google.com/p/go.crypto/",
	"modified": "2013-07-16 23:36:34.175100"
}