{
	"files": {
		"src/pkg/net/ipsock_plan9.go": {
			"status": "M",
			"num_chunks": 1,
			"no_base_file": false,
			"property_changes": "",
			"num_added": 2,
			"num_removed": 0,
			"id": 1004,
			"is_binary": false
		},
		"src/pkg/net/timeout_test.go": {
			"status": "M",
			"num_chunks": 1,
			"no_base_file": false,
			"property_changes": "",
			"num_added": 9,
			"num_removed": 4,
			"id": 1005,
			"is_binary": false
		}
	},
	"url": null,
	"created": "2012-11-04 01:41:41.873860",
	"owner": "brainman",
	"num_comments": 1,
	"patchset": 5004,
	"owner_email": "alex.brainman@gmail.com",
	"issue": 6821062,
	"message": "diff -r 126c37a9e33c https://go.googlecode.com/hg/",
	"modified": "2012-11-04 09:32:12.058280"
}