{
	"files": {
		"src/pkg/strings/strings.go": {
			"status": "M",
			"num_chunks": 3,
			"no_base_file": false,
			"property_changes": "",
			"num_added": 13,
			"num_removed": 3,
			"id": 8002,
			"is_binary": false
		},
		"src/pkg/strings/strings_test.go": {
			"status": "M",
			"num_chunks": 1,
			"no_base_file": false,
			"property_changes": "",
			"num_added": 50,
			"num_removed": 0,
			"id": 8003,
			"is_binary": false
		}
	},
	"url": null,
	"created": "2011-11-24 04:15:44.528400",
	"owner": "bytbox",
	"num_comments": 0,
	"patchset": 1005,
	"owner_email": "bytbox@gmail.com",
	"issue": 5430046,
	"message": "diff -r 1b010352ab57 https://go.googlecode.com/hg/",
	"modified": "2011-11-24 04:15:44.528664"
}