{
	"files": {
		"src/cmd/gc/align.c": {
			"status": "M",
			"num_chunks": 1,
			"no_base_file": false,
			"property_changes": "",
			"num_added": 2,
			"num_removed": 0,
			"id": 16001,
			"is_binary": false
		},
		"test/typecheck.go": {
			"status": "A",
			"num_chunks": 1,
			"no_base_file": false,
			"property_changes": "",
			"num_added": 18,
			"num_removed": 0,
			"id": 16002,
			"is_binary": false
		}
	},
	"url": null,
	"created": "2012-10-05 21:22:20.174520",
	"owner": "akumar",
	"num_comments": 0,
	"patchset": 15002,
	"owner_email": "seed@mail.nanosouffle.net",
	"issue": 6542060,
	"message": "diff -r 53a8e1ce580e https://go.googlecode.com/hg/",
	"modified": "2012-10-05 21:22:20.175050"
}