{
	"files": {
		"src/cmd/gc/typecheck.c": {
			"status": "M",
			"num_chunks": 1,
			"no_base_file": false,
			"property_changes": "",
			"num_added": 1,
			"num_removed": 0,
			"id": 3002,
			"is_binary": false
		},
		"src/cmd/gc/fmt.c": {
			"status": "M",
			"num_chunks": 4,
			"no_base_file": false,
			"property_changes": "",
			"num_added": 4,
			"num_removed": 7,
			"id": 3001,
			"is_binary": false
		}
	},
	"url": null,
	"created": "2011-11-01 10:17:30.866358",
	"owner": "lvd",
	"num_comments": 0,
	"patchset": 2001,
	"owner_email": "lvd@google.com",
	"issue": 5319065,
	"message": "diff -r cffdcf22fc7b https://go.googlecode.com/hg/",
	"modified": "2011-11-01 10:17:30.866706"
}