{
	"files": {
		"src/pkg/encoding/xml/xml_test.go": {
			"status": "M",
			"num_chunks": 2,
			"no_base_file": false,
			"property_changes": "",
			"num_added": 21,
			"num_removed": 21,
			"id": 11,
			"is_binary": false
		},
		"src/pkg/encoding/xml/read.go": {
			"status": "M",
			"num_chunks": 14,
			"no_base_file": false,
			"property_changes": "",
			"num_added": 134,
			"num_removed": 203,
			"id": 8,
			"is_binary": false
		},
		"src/pkg/encoding/xml/Makefile": {
			"status": "M",
			"num_chunks": 1,
			"no_base_file": false,
			"property_changes": "",
			"num_added": 1,
			"num_removed": 0,
			"id": 4,
			"is_binary": false
		},
		"src/pkg/encoding/xml/typeinfo.go": {
			"status": "A",
			"num_chunks": 1,
			"no_base_file": false,
			"property_changes": "",
			"num_added": 346,
			"num_removed": 0,
			"id": 10,
			"is_binary": false
		},
		"src/pkg/encoding/xml/marshal.go": {
			"status": "M",
			"num_chunks": 6,
			"no_base_file": false,
			"property_changes": "",
			"num_added": 127,
			"num_removed": 90,
			"id": 6,
			"is_binary": false
		},
		"src/pkg/encoding/xml/atom_test.go": {
			"status": "M",
			"num_chunks": 2,
			"no_base_file": false,
			"property_changes": "",
			"num_added": 14,
			"num_removed": 13,
			"id": 5,
			"is_binary": false
		},
		"src/pkg/encoding/xml/read_test.go": {
			"status": "M",
			"num_chunks": 7,
			"no_base_file": false,
			"property_changes": "",
			"num_added": 68,
			"num_removed": 112,
			"id": 9,
			"is_binary": false
		},
		"src/pkg/encoding/xml/marshal_test.go": {
			"status": "M",
			"num_chunks": 14,
			"no_base_file": false,
			"property_changes": "",
			"num_added": 304,
			"num_removed": 109,
			"id": 7,
			"is_binary": false
		}
	},
	"url": null,
	"created": "2011-12-29 05:39:16.128044",
	"owner": "niemeyer",
	"num_comments": 0,
	"patchset": 1002,
	"owner_email": "n13m3y3r@gmail.com",
	"issue": 5503078,
	"message": "diff -r 7ec969250bfc https://go.googlecode.com/hg/",
	"modified": "2011-12-29 05:39:16.128355"
}