{
	"files": {
		"mssql_test.go": {
			"status": "M",
			"num_chunks": 3,
			"no_base_file": false,
			"property_changes": "",
			"num_added": 12,
			"num_removed": 9,
			"id": 9004,
			"is_binary": false
		},
		"api/api_unix.go": {
			"status": "M",
			"num_chunks": 1,
			"no_base_file": false,
			"property_changes": "",
			"num_added": 3,
			"num_removed": 0,
			"id": 9001,
			"is_binary": false
		},
		"column.go": {
			"status": "M",
			"num_chunks": 2,
			"no_base_file": false,
			"property_changes": "",
			"num_added": 2,
			"num_removed": 2,
			"id": 9003,
			"is_binary": false
		},
		"api/api_windows.go": {
			"status": "M",
			"num_chunks": 1,
			"no_base_file": false,
			"property_changes": "",
			"num_added": 1,
			"num_removed": 0,
			"id": 9002,
			"is_binary": false
		}
	},
	"url": null,
	"created": "2013-04-25 11:38:08.646680",
	"owner": "lukemauldin",
	"num_comments": 0,
	"patchset": 8001,
	"owner_email": "lukemauldin@gmail.com",
	"issue": 8751045,
	"message": "diff -r 0cc05e8b93ee https://code.google.com/p/odbc",
	"modified": "2013-04-25 11:38:08.647050"
}