{
	"files": {
		"src/cmd/8g/reg.c": {
			"status": "M",
			"num_chunks": 13,
			"no_base_file": false,
			"property_changes": "",
			"num_added": 86,
			"num_removed": 5,
			"id": 33008,
			"is_binary": false
		},
		"src/cmd/8g/peep.c": {
			"status": "M",
			"num_chunks": 10,
			"no_base_file": false,
			"property_changes": "",
			"num_added": 64,
			"num_removed": 2,
			"id": 33007,
			"is_binary": false
		},
		"src/cmd/8g/cgen.c": {
			"status": "M",
			"num_chunks": 11,
			"no_base_file": false,
			"property_changes": "",
			"num_added": 21,
			"num_removed": 113,
			"id": 33002,
			"is_binary": false
		},
		"src/cmd/gc/go.h": {
			"status": "M",
			"num_chunks": 1,
			"no_base_file": false,
			"property_changes": "",
			"num_added": 1,
			"num_removed": 0,
			"id": 33010,
			"is_binary": false
		},
		"src/cmd/gc/lex.c": {
			"status": "M",
			"num_chunks": 1,
			"no_base_file": false,
			"property_changes": "",
			"num_added": 1,
			"num_removed": 0,
			"id": 33011,
			"is_binary": false
		},
		"src/lib9/goos.c": {
			"status": "M",
			"num_chunks": 1,
			"no_base_file": false,
			"property_changes": "",
			"num_added": 6,
			"num_removed": 0,
			"id": 33012,
			"is_binary": false
		},
		"include/libc.h": {
			"status": "M",
			"num_chunks": 1,
			"no_base_file": false,
			"property_changes": "",
			"num_added": 1,
			"num_removed": 0,
			"id": 33001,
			"is_binary": false
		},
		"src/cmd/8g/gsubr.c": {
			"status": "M",
			"num_chunks": 16,
			"no_base_file": false,
			"property_changes": "",
			"num_added": 492,
			"num_removed": 138,
			"id": 33005,
			"is_binary": false
		},
		"src/cmd/dist/build.c": {
			"status": "M",
			"num_chunks": 5,
			"no_base_file": false,
			"property_changes": "",
			"num_added": 10,
			"num_removed": 0,
			"id": 33009,
			"is_binary": false
		},
		"src/cmd/8g/list.c": {
			"status": "M",
			"num_chunks": 1,
			"no_base_file": false,
			"property_changes": "",
			"num_added": 9,
			"num_removed": 0,
			"id": 33006,
			"is_binary": false
		},
		"src/cmd/8g/ggen.c": {
			"status": "M",
			"num_chunks": 1,
			"no_base_file": false,
			"property_changes": "",
			"num_added": 307,
			"num_removed": 0,
			"id": 33004,
			"is_binary": false
		},
		"src/cmd/8g/gg.h": {
			"status": "M",
			"num_chunks": 1,
			"no_base_file": false,
			"property_changes": "",
			"num_added": 2,
			"num_removed": 0,
			"id": 33003,
			"is_binary": false
		}
	},
	"url": null,
	"created": "2013-01-02 21:55:12.837790",
	"owner": "remyoudompheng",
	"num_comments": 0,
	"patchset": 29003,
	"owner_email": "remyoudompheng@gmail.com",
	"issue": 6962043,
	"message": "diff -r b2bc77ca3160 https://go.googlecode.com/hg/",
	"modified": "2013-01-02 21:55:12.838350"
}