{
	"files": {
		"src/pkg/crypto/ecdsa/ecdsa.go": {
			"status": "M",
			"num_chunks": 1,
			"no_base_file": false,
			"property_changes": "",
			"num_added": 1,
			"num_removed": 1,
			"id": 11010,
			"is_binary": false
		},
		"src/pkg/math/bits.go": {
			"status": "M",
			"num_chunks": 2,
			"no_base_file": false,
			"property_changes": "",
			"num_added": 5,
			"num_removed": 5,
			"id": 11045,
			"is_binary": false
		},
		"src/pkg/crypto/dsa/dsa.go": {
			"status": "M",
			"num_chunks": 1,
			"no_base_file": false,
			"property_changes": "",
			"num_added": 1,
			"num_removed": 1,
			"id": 11009,
			"is_binary": false
		},
		"src/pkg/os/path_plan9.go": {
			"status": "M",
			"num_chunks": 1,
			"no_base_file": false,
			"property_changes": "",
			"num_added": 1,
			"num_removed": 1,
			"id": 11050,
			"is_binary": false
		},
		"src/pkg/exp/eval/stmt.go": {
			"status": "M",
			"num_chunks": 2,
			"no_base_file": false,
			"property_changes": "",
			"num_added": 2,
			"num_removed": 2,
			"id": 11022,
			"is_binary": false
		},
		"src/pkg/testing/script/script.go": {
			"status": "M",
			"num_chunks": 1,
			"no_base_file": false,
			"property_changes": "",
			"num_added": 1,
			"num_removed": 1,
			"id": 11071,
			"is_binary": false
		},
		"src/pkg/mime/grammar.go": {
			"status": "M",
			"num_chunks": 2,
			"no_base_file": false,
			"property_changes": "",
			"num_added": 3,
			"num_removed": 3,
			"id": 11047,
			"is_binary": false
		},
		"src/pkg/image/names.go": {
			"status": "M",
			"num_chunks": 1,
			"no_base_file": false,
			"property_changes": "",
			"num_added": 1,
			"num_removed": 1,
			"id": 11042,
			"is_binary": false
		},
		"src/pkg/path/filepath/match.go": {
			"status": "M",
			"num_chunks": 2,
			"no_base_file": false,
			"property_changes": "",
			"num_added": 2,
			"num_removed": 2,
			"id": 11054,
			"is_binary": false
		},
		"src/pkg/net/tcpsock.go": {
			"status": "M",
			"num_chunks": 1,
			"no_base_file": false,
			"property_changes": "",
			"num_added": 1,
			"num_removed": 1,
			"id": 11049,
			"is_binary": false
		},
		"src/pkg/crypto/x509/crl/crl.go": {
			"status": "M",
			"num_chunks": 1,
			"no_base_file": false,
			"property_changes": "",
			"num_added": 1,
			"num_removed": 1,
			"id": 11018,
			"is_binary": false
		},
		"src/pkg/os/path_windows.go": {
			"status": "M",
			"num_chunks": 1,
			"no_base_file": false,
			"property_changes": "",
			"num_added": 1,
			"num_removed": 1,
			"id": 11052,
			"is_binary": false
		},
		"src/pkg/json/decode.go": {
			"status": "M",
			"num_chunks": 1,
			"no_base_file": false,
			"property_changes": "",
			"num_added": 1,
			"num_removed": 1,
			"id": 11044,
			"is_binary": false
		},
		"src/pkg/reflect/type.go": {
			"status": "M",
			"num_chunks": 4,
			"no_base_file": false,
			"property_changes": "",
			"num_added": 5,
			"num_removed": 5,
			"id": 11061,
			"is_binary": false
		},
		"src/pkg/time/sleep.go": {
			"status": "M",
			"num_chunks": 1,
			"no_base_file": false,
			"property_changes": "",
			"num_added": 1,
			"num_removed": 1,
			"id": 11073,
			"is_binary": false
		},
		"src/pkg/template/template.go": {
			"status": "M",
			"num_chunks": 1,
			"no_base_file": false,
			"property_changes": "",
			"num_added": 1,
			"num_removed": 1,
			"id": 11070,
			"is_binary": false
		},
		"src/pkg/go/parser/parser.go": {
			"status": "M",
			"num_chunks": 2,
			"no_base_file": false,
			"property_changes": "",
			"num_added": 2,
			"num_removed": 2,
			"id": 11029,
			"is_binary": false
		},
		"src/pkg/go/token/position.go": {
			"status": "M",
			"num_chunks": 3,
			"no_base_file": false,
			"property_changes": "",
			"num_added": 3,
			"num_removed": 3,
			"id": 11032,
			"is_binary": false
		},
		"src/pkg/bytes/bytes.go": {
			"status": "M",
			"num_chunks": 2,
			"no_base_file": false,
			"property_changes": "",
			"num_added": 3,
			"num_removed": 3,
			"id": 11004,
			"is_binary": false
		},
		"src/pkg/path/path.go": {
			"status": "M",
			"num_chunks": 1,
			"no_base_file": false,
			"property_changes": "",
			"num_added": 1,
			"num_removed": 1,
			"id": 11060,
			"is_binary": false
		},
		"src/pkg/fmt/print.go": {
			"status": "M",
			"num_chunks": 1,
			"no_base_file": false,
			"property_changes": "",
			"num_added": 1,
			"num_removed": 1,
			"id": 11026,
			"is_binary": false
		},
		"src/pkg/compress/bzip2/bzip2.go": {
			"status": "M",
			"num_chunks": 1,
			"no_base_file": false,
			"property_changes": "",
			"num_added": 1,
			"num_removed": 1,
			"id": 11007,
			"is_binary": false
		},
		"src/pkg/crypto/x509/x509.go": {
			"status": "M",
			"num_chunks": 1,
			"no_base_file": false,
			"property_changes": "",
			"num_added": 1,
			"num_removed": 1,
			"id": 11019,
			"is_binary": false
		},
		"src/pkg/debug/gosym/symtab.go": {
			"status": "M",
			"num_chunks": 1,
			"no_base_file": false,
			"property_changes": "",
			"num_added": 1,
			"num_removed": 1,
			"id": 11020,
			"is_binary": false
		},
		"src/pkg/exp/ogle/goroutine.go": {
			"status": "M",
			"num_chunks": 1,
			"no_base_file": false,
			"property_changes": "",
			"num_added": 1,
			"num_removed": 1,
			"id": 11024,
			"is_binary": false
		},
		"src/pkg/path/filepath/path_unix.go": {
			"status": "M",
			"num_chunks": 1,
			"no_base_file": false,
			"property_changes": "",
			"num_added": 1,
			"num_removed": 1,
			"id": 11057,
			"is_binary": false
		},
		"src/pkg/http/transport.go": {
			"status": "M",
			"num_chunks": 1,
			"no_base_file": false,
			"property_changes": "",
			"num_added": 1,
			"num_removed": 1,
			"id": 11037,
			"is_binary": false
		},
		"src/pkg/asn1/common.go": {
			"status": "M",
			"num_chunks": 1,
			"no_base_file": false,
			"property_changes": "",
			"num_added": 4,
			"num_removed": 4,
			"id": 11002,
			"is_binary": false
		},
		"src/pkg/path/filepath/path_plan9.go": {
			"status": "M",
			"num_chunks": 1,
			"no_base_file": false,
			"property_changes": "",
			"num_added": 1,
			"num_removed": 1,
			"id": 11056,
			"is_binary": false
		},
		"src/pkg/crypto/openpgp/packet/symmetrically_encrypted.go": {
			"status": "M",
			"num_chunks": 1,
			"no_base_file": false,
			"property_changes": "",
			"num_added": 1,
			"num_removed": 1,
			"id": 11015,
			"is_binary": false
		},
		"src/pkg/crypto/openpgp/packet/literal.go": {
			"status": "M",
			"num_chunks": 1,
			"no_base_file": false,
			"property_changes": "",
			"num_added": 1,
			"num_removed": 1,
			"id": 11012,
			"is_binary": false
		},
		"src/pkg/testing/testing.go": {
			"status": "M",
			"num_chunks": 1,
			"no_base_file": false,
			"property_changes": "",
			"num_added": 1,
			"num_removed": 1,
			"id": 11072,
			"is_binary": false
		},
		"src/pkg/crypto/openpgp/packet/signature.go": {
			"status": "M",
			"num_chunks": 1,
			"no_base_file": false,
			"property_changes": "",
			"num_added": 1,
			"num_removed": 1,
			"id": 11014,
			"is_binary": false
		},
		"src/pkg/image/png/writer.go": {
			"status": "M",
			"num_chunks": 1,
			"no_base_file": false,
			"property_changes": "",
			"num_added": 1,
			"num_removed": 1,
			"id": 11043,
			"is_binary": false
		},
		"src/pkg/utf8/string.go": {
			"status": "M",
			"num_chunks": 1,
			"no_base_file": false,
			"property_changes": "",
			"num_added": 1,
			"num_removed": 1,
			"id": 11076,
			"is_binary": false
		},
		"src/pkg/regexp/regexp.go": {
			"status": "M",
			"num_chunks": 4,
			"no_base_file": false,
			"property_changes": "",
			"num_added": 9,
			"num_removed": 9,
			"id": 11063,
			"is_binary": false
		},
		"src/pkg/cmath/isinf.go": {
			"status": "M",
			"num_chunks": 1,
			"no_base_file": false,
			"property_changes": "",
			"num_added": 1,
			"num_removed": 1,
			"id": 11005,
			"is_binary": false
		},
		"src/pkg/flag/flag.go": {
			"status": "M",
			"num_chunks": 3,
			"no_base_file": false,
			"property_changes": "",
			"num_added": 3,
			"num_removed": 3,
			"id": 11025,
			"is_binary": false
		},
		"src/pkg/reflect/value.go": {
			"status": "M",
			"num_chunks": 10,
			"no_base_file": false,
			"property_changes": "",
			"num_added": 10,
			"num_removed": 10,
			"id": 11062,
			"is_binary": false
		},
		"src/pkg/image/geom.go": {
			"status": "M",
			"num_chunks": 3,
			"no_base_file": false,
			"property_changes": "",
			"num_added": 6,
			"num_removed": 6,
			"id": 11040,
			"is_binary": false
		},
		"src/pkg/go/printer/testdata/parser.go": {
			"status": "M",
			"num_chunks": 2,
			"no_base_file": false,
			"property_changes": "",
			"num_added": 2,
			"num_removed": 2,
			"id": 11031,
			"is_binary": false
		},
		"src/pkg/http/response.go": {
			"status": "M",
			"num_chunks": 1,
			"no_base_file": false,
			"property_changes": "",
			"num_added": 1,
			"num_removed": 1,
			"id": 11035,
			"is_binary": false
		},
		"src/pkg/debug/proc/proc.go": {
			"status": "M",
			"num_chunks": 1,
			"no_base_file": false,
			"property_changes": "",
			"num_added": 2,
			"num_removed": 2,
			"id": 11021,
			"is_binary": false
		},
		"src/pkg/go/ast/filter.go": {
			"status": "M",
			"num_chunks": 5,
			"no_base_file": false,
			"property_changes": "",
			"num_added": 5,
			"num_removed": 5,
			"id": 11028,
			"is_binary": false
		},
		"src/pkg/path/match.go": {
			"status": "M",
			"num_chunks": 1,
			"no_base_file": false,
			"property_changes": "",
			"num_added": 1,
			"num_removed": 1,
			"id": 11059,
			"is_binary": false
		},
		"src/pkg/strings/strings.go": {
			"status": "M",
			"num_chunks": 2,
			"no_base_file": false,
			"property_changes": "",
			"num_added": 3,
			"num_removed": 3,
			"id": 11068,
			"is_binary": false
		},
		"src/pkg/cmath/isnan.go": {
			"status": "M",
			"num_chunks": 1,
			"no_base_file": false,
			"property_changes": "",
			"num_added": 1,
			"num_removed": 1,
			"id": 11006,
			"is_binary": false
		},
		"src/pkg/crypto/openpgp/read.go": {
			"status": "M",
			"num_chunks": 1,
			"no_base_file": false,
			"property_changes": "",
			"num_added": 3,
			"num_removed": 3,
			"id": 11016,
			"is_binary": false
		},
		"src/pkg/utf16/utf16.go": {
			"status": "M",
			"num_chunks": 1,
			"no_base_file": false,
			"property_changes": "",
			"num_added": 1,
			"num_removed": 1,
			"id": 11075,
			"is_binary": false
		},
		"src/pkg/patch/patch.go": {
			"status": "M",
			"num_chunks": 1,
			"no_base_file": false,
			"property_changes": "",
			"num_added": 1,
			"num_removed": 1,
			"id": 11053,
			"is_binary": false
		},
		"src/pkg/crypto/elliptic/elliptic.go": {
			"status": "M",
			"num_chunks": 1,
			"no_base_file": false,
			"property_changes": "",
			"num_added": 1,
			"num_removed": 1,
			"id": 11011,
			"is_binary": false
		},
		"src/pkg/math/signbit.go": {
			"status": "M",
			"num_chunks": 1,
			"no_base_file": false,
			"property_changes": "",
			"num_added": 1,
			"num_removed": 1,
			"id": 11046,
			"is_binary": false
		},
		"src/pkg/go/types/types.go": {
			"status": "M",
			"num_chunks": 3,
			"no_base_file": false,
			"property_changes": "",
			"num_added": 3,
			"num_removed": 3,
			"id": 11033,
			"is_binary": false
		},
		"src/pkg/image/image.go": {
			"status": "M",
			"num_chunks": 9,
			"no_base_file": false,
			"property_changes": "",
			"num_added": 9,
			"num_removed": 9,
			"id": 11041,
			"is_binary": false
		},
		"src/pkg/container/vector/defs.go": {
			"status": "M",
			"num_chunks": 1,
			"no_base_file": false,
			"property_changes": "",
			"num_added": 3,
			"num_removed": 3,
			"id": 11008,
			"is_binary": false
		},
		"src/pkg/exp/eval/type.go": {
			"status": "M",
			"num_chunks": 1,
			"no_base_file": false,
			"property_changes": "",
			"num_added": 4,
			"num_removed": 4,
			"id": 11023,
			"is_binary": false
		},
		"src/pkg/crypto/x509/cert_pool.go": {
			"status": "M",
			"num_chunks": 1,
			"no_base_file": false,
			"property_changes": "",
			"num_added": 1,
			"num_removed": 1,
			"id": 11017,
			"is_binary": false
		},
		"src/pkg/crypto/openpgp/packet/public_key.go": {
			"status": "M",
			"num_chunks": 1,
			"no_base_file": false,
			"property_changes": "",
			"num_added": 1,
			"num_removed": 1,
			"id": 11013,
			"is_binary": false
		},
		"src/pkg/image/format.go": {
			"status": "M",
			"num_chunks": 1,
			"no_base_file": false,
			"property_changes": "",
			"num_added": 1,
			"num_removed": 1,
			"id": 11039,
			"is_binary": false
		},
		"src/pkg/go/printer/printer.go": {
			"status": "M",
			"num_chunks": 4,
			"no_base_file": false,
			"property_changes": "",
			"num_added": 4,
			"num_removed": 4,
			"id": 11030,
			"is_binary": false
		},
		"src/pkg/path/filepath/path_windows.go": {
			"status": "M",
			"num_chunks": 1,
			"no_base_file": false,
			"property_changes": "",
			"num_added": 1,
			"num_removed": 1,
			"id": 11058,
			"is_binary": false
		},
		"src/pkg/path/filepath/match_test.go": {
			"status": "M",
			"num_chunks": 1,
			"no_base_file": false,
			"property_changes": "",
			"num_added": 1,
			"num_removed": 1,
			"id": 11055,
			"is_binary": false
		},
		"src/pkg/http/url.go": {
			"status": "M",
			"num_chunks": 1,
			"no_base_file": false,
			"property_changes": "",
			"num_added": 1,
			"num_removed": 1,
			"id": 11038,
			"is_binary": false
		},
		"src/pkg/asn1/asn1.go": {
			"status": "M",
			"num_chunks": 3,
			"no_base_file": false,
			"property_changes": "",
			"num_added": 3,
			"num_removed": 3,
			"id": 11001,
			"is_binary": false
		},
		"src/pkg/unicode/letter.go": {
			"status": "M",
			"num_chunks": 3,
			"no_base_file": false,
			"property_changes": "",
			"num_added": 3,
			"num_removed": 3,
			"id": 11074,
			"is_binary": false
		},
		"src/pkg/runtime/cpuprof.c": {
			"status": "M",
			"num_chunks": 1,
			"no_base_file": false,
			"property_changes": "",
			"num_added": 1,
			"num_removed": 1,
			"id": 11064,
			"is_binary": false
		},
		"src/pkg/go/ast/ast.go": {
			"status": "M",
			"num_chunks": 4,
			"no_base_file": false,
			"property_changes": "",
			"num_added": 6,
			"num_removed": 6,
			"id": 11027,
			"is_binary": false
		},
		"src/pkg/os/path_unix.go": {
			"status": "M",
			"num_chunks": 1,
			"no_base_file": false,
			"property_changes": "",
			"num_added": 1,
			"num_removed": 1,
			"id": 11051,
			"is_binary": false
		},
		"src/pkg/strconv/quote.go": {
			"status": "M",
			"num_chunks": 1,
			"no_base_file": false,
			"property_changes": "",
			"num_added": 1,
			"num_removed": 1,
			"id": 11067,
			"is_binary": false
		},
		"src/pkg/http/transfer.go": {
			"status": "M",
			"num_chunks": 1,
			"no_base_file": false,
			"property_changes": "",
			"num_added": 1,
			"num_removed": 1,
			"id": 11036,
			"is_binary": false
		},
		"src/pkg/net/ip.go": {
			"status": "M",
			"num_chunks": 7,
			"no_base_file": false,
			"property_changes": "",
			"num_added": 8,
			"num_removed": 8,
			"id": 11048,
			"is_binary": false
		},
		"src/pkg/big/rat.go": {
			"status": "M",
			"num_chunks": 1,
			"no_base_file": false,
			"property_changes": "",
			"num_added": 1,
			"num_removed": 1,
			"id": 11003,
			"is_binary": false
		},
		"src/pkg/scanner/scanner.go": {
			"status": "M",
			"num_chunks": 1,
			"no_base_file": false,
			"property_changes": "",
			"num_added": 1,
			"num_removed": 1,
			"id": 11065,
			"is_binary": false
		},
		"src/pkg/http/request.go": {
			"status": "M",
			"num_chunks": 1,
			"no_base_file": false,
			"property_changes": "",
			"num_added": 1,
			"num_removed": 1,
			"id": 11034,
			"is_binary": false
		},
		"src/pkg/tabwriter/tabwriter.go": {
			"status": "M",
			"num_chunks": 2,
			"no_base_file": false,
			"property_changes": "",
			"num_added": 2,
			"num_removed": 2,
			"id": 11069,
			"is_binary": false
		},
		"src/pkg/sort/sort.go": {
			"status": "M",
			"num_chunks": 2,
			"no_base_file": false,
			"property_changes": "",
			"num_added": 7,
			"num_removed": 7,
			"id": 11066,
			"is_binary": false
		}
	},
	"url": null,
	"created": "2011-06-03 14:57:39.560013",
	"owner": "rsc",
	"num_comments": 0,
	"patchset": 10001,
	"owner_email": "rsc@golang.org",
	"issue": 4551089,
	"message": "diff -r fa2bae213af8 https://go.googlecode.com/hg",
	"modified": "2011-06-03 14:57:39.560373"
}