{
	"files": {
		"graphics/detect/doc.go": {
			"status": "A",
			"num_chunks": 1,
			"no_base_file": false,
			"property_changes": "",
			"num_added": 31,
			"num_removed": 0,
			"id": 12004,
			"is_binary": false
		},
		"graphics/detect/integral_test.go": {
			"status": "A",
			"num_chunks": 1,
			"no_base_file": false,
			"property_changes": "",
			"num_added": 163,
			"num_removed": 0,
			"id": 12006,
			"is_binary": false
		},
		"graphics/detect/detect.go": {
			"status": "A",
			"num_chunks": 1,
			"no_base_file": false,
			"property_changes": "",
			"num_added": 131,
			"num_removed": 0,
			"id": 12002,
			"is_binary": false
		},
		"graphics/detect/projector.go": {
			"status": "A",
			"num_chunks": 1,
			"no_base_file": false,
			"property_changes": "",
			"num_added": 54,
			"num_removed": 0,
			"id": 12009,
			"is_binary": false
		},
		"graphics/detect/detect_test.go": {
			"status": "A",
			"num_chunks": 1,
			"no_base_file": false,
			"property_changes": "",
			"num_added": 79,
			"num_removed": 0,
			"id": 12003,
			"is_binary": false
		},
		"graphics/detect/integral.go": {
			"status": "A",
			"num_chunks": 1,
			"no_base_file": false,
			"property_changes": "",
			"num_added": 126,
			"num_removed": 0,
			"id": 12005,
			"is_binary": false
		},
		"graphics/detect/projector_test.go": {
			"status": "A",
			"num_chunks": 1,
			"no_base_file": false,
			"property_changes": "",
			"num_added": 49,
			"num_removed": 0,
			"id": 12010,
			"is_binary": false
		},
		"graphics/detect/opencv_parser_test.go": {
			"status": "A",
			"num_chunks": 1,
			"no_base_file": false,
			"property_changes": "",
			"num_added": 78,
			"num_removed": 0,
			"id": 12008,
			"is_binary": false
		},
		"graphics/detect/Makefile": {
			"status": "A",
			"num_chunks": 1,
			"no_base_file": false,
			"property_changes": "",
			"num_added": 14,
			"num_removed": 0,
			"id": 12001,
			"is_binary": false
		},
		"graphics/detect/opencv_parser.go": {
			"status": "A",
			"num_chunks": 1,
			"no_base_file": false,
			"property_changes": "",
			"num_added": 125,
			"num_removed": 0,
			"id": 12007,
			"is_binary": false
		},
		"testdata/opencv.xml": {
			"status": "A",
			"num_chunks": 1,
			"no_base_file": false,
			"property_changes": "",
			"num_added": 66,
			"num_removed": 0,
			"id": 12011,
			"is_binary": false
		}
	},
	"url": null,
	"created": "2011-10-22 15:54:00.104739",
	"owner": "crawshaw1",
	"num_comments": 22,
	"patchset": 11001,
	"owner_email": "crawshaw@google.com",
	"issue": 5229053,
	"message": "diff -r c1ee317244e6 https://crawshaw%40google.com@code.google.com/p/graphics-go/",
	"modified": "2011-11-01 05:15:03.753253"
}