{
	"files": {
		"src/cmd/8g/prog.c": {
			"status": "M",
			"num_chunks": 3,
			"no_base_file": false,
			"property_changes": "",
			"num_added": 9,
			"num_removed": 9,
			"id": 1002,
			"is_binary": false
		},
		"src/cmd/6g/prog.c": {
			"status": "M",
			"num_chunks": 2,
			"no_base_file": false,
			"property_changes": "",
			"num_added": 12,
			"num_removed": 12,
			"id": 1001,
			"is_binary": false
		}
	},
	"url": null,
	"created": "2013-08-12 23:17:50.994800",
	"owner": "rsc",
	"num_comments": 0,
	"patchset": 1,
	"owner_email": "rsc@golang.org",
	"issue": 12815043,
	"message": null,
	"modified": "2013-08-12 23:17:50.995430"
}