{
	"files": {
		"src/pkg/syscall/zsyscall_openbsd_386.go": {
			"status": "M",
			"num_chunks": 1,
			"no_base_file": false,
			"property_changes": "",
			"num_added": 1,
			"num_removed": 1,
			"id": 16,
			"is_binary": false
		},
		"src/pkg/syscall/syscall_linux.go": {
			"status": "M",
			"num_chunks": 1,
			"no_base_file": false,
			"property_changes": "",
			"num_added": 6,
			"num_removed": 1,
			"id": 4,
			"is_binary": false
		},
		"src/pkg/syscall/syscall_linux_amd64.go": {
			"status": "M",
			"num_chunks": 1,
			"no_base_file": false,
			"property_changes": "",
			"num_added": 1,
			"num_removed": 1,
			"id": 6,
			"is_binary": false
		},
		"src/pkg/syscall/zsyscall_darwin_amd64.go": {
			"status": "M",
			"num_chunks": 1,
			"no_base_file": false,
			"property_changes": "",
			"num_added": 1,
			"num_removed": 1,
			"id": 9,
			"is_binary": false
		},
		"src/pkg/syscall/zsyscall_linux_amd64.go": {
			"status": "M",
			"num_chunks": 1,
			"no_base_file": false,
			"property_changes": "",
			"num_added": 1,
			"num_removed": 1,
			"id": 12,
			"is_binary": false
		},
		"src/pkg/syscall/zsyscall_darwin_386.go": {
			"status": "M",
			"num_chunks": 1,
			"no_base_file": false,
			"property_changes": "",
			"num_added": 1,
			"num_removed": 1,
			"id": 8,
			"is_binary": false
		},
		"src/pkg/syscall/zsyscall_linux_arm.go": {
			"status": "M",
			"num_chunks": 1,
			"no_base_file": false,
			"property_changes": "",
			"num_added": 1,
			"num_removed": 1,
			"id": 13,
			"is_binary": false
		},
		"src/pkg/syscall/syscall_linux_386.go": {
			"status": "M",
			"num_chunks": 1,
			"no_base_file": false,
			"property_changes": "",
			"num_added": 1,
			"num_removed": 1,
			"id": 5,
			"is_binary": false
		},
		"src/pkg/syscall/zsyscall_netbsd_386.go": {
			"status": "M",
			"num_chunks": 1,
			"no_base_file": false,
			"property_changes": "",
			"num_added": 1,
			"num_removed": 1,
			"id": 14,
			"is_binary": false
		},
		"src/pkg/syscall/syscall_linux_arm.go": {
			"status": "M",
			"num_chunks": 1,
			"no_base_file": false,
			"property_changes": "",
			"num_added": 1,
			"num_removed": 1,
			"id": 7,
			"is_binary": false
		},
		"src/pkg/syscall/zsyscall_netbsd_amd64.go": {
			"status": "M",
			"num_chunks": 1,
			"no_base_file": false,
			"property_changes": "",
			"num_added": 1,
			"num_removed": 1,
			"id": 15,
			"is_binary": false
		},
		"src/pkg/syscall/zsyscall_freebsd_386.go": {
			"status": "M",
			"num_chunks": 1,
			"no_base_file": false,
			"property_changes": "",
			"num_added": 1,
			"num_removed": 1,
			"id": 10,
			"is_binary": false
		},
		"src/pkg/syscall/zsyscall_freebsd_amd64.go": {
			"status": "M",
			"num_chunks": 1,
			"no_base_file": false,
			"property_changes": "",
			"num_added": 1,
			"num_removed": 1,
			"id": 11,
			"is_binary": false
		},
		"src/pkg/syscall/zsyscall_openbsd_amd64.go": {
			"status": "M",
			"num_chunks": 1,
			"no_base_file": false,
			"property_changes": "",
			"num_added": 1,
			"num_removed": 1,
			"id": 17,
			"is_binary": false
		},
		"src/pkg/syscall/syscall_bsd.go": {
			"status": "M",
			"num_chunks": 1,
			"no_base_file": false,
			"property_changes": "",
			"num_added": 7,
			"num_removed": 2,
			"id": 3,
			"is_binary": false
		}
	},
	"url": null,
	"created": "2012-09-24 04:06:16.691860",
	"owner": "rsc",
	"num_comments": 0,
	"patchset": 6002,
	"owner_email": "rsc@golang.org",
	"issue": 6552063,
	"message": "diff -r 74370b0a2b8a https://code.google.com/p/go/",
	"modified": "2012-09-24 04:06:16.692160"
}