{
	"files": {
		"src/pkg/reflect/asm_386.s": {
			"status": "A",
			"num_chunks": 1,
			"no_base_file": false,
			"property_changes": "",
			"num_added": 18,
			"num_removed": 0,
			"id": 10004,
			"is_binary": false
		},
		"src/pkg/reflect/example_test.go": {
			"status": "A",
			"num_chunks": 1,
			"no_base_file": false,
			"property_changes": "",
			"num_added": 52,
			"num_removed": 0,
			"id": 10007,
			"is_binary": false
		},
		"src/pkg/reflect/asm_amd64.s": {
			"status": "A",
			"num_chunks": 1,
			"no_base_file": false,
			"property_changes": "",
			"num_added": 18,
			"num_removed": 0,
			"id": 10005,
			"is_binary": false
		},
		"src/pkg/reflect/all_test.go": {
			"status": "M",
			"num_chunks": 1,
			"no_base_file": false,
			"property_changes": "",
			"num_added": 40,
			"num_removed": 7,
			"id": 10003,
			"is_binary": false
		},
		"src/pkg/reflect/value.go": {
			"status": "M",
			"num_chunks": 1,
			"no_base_file": false,
			"property_changes": "",
			"num_added": 76,
			"num_removed": 0,
			"id": 10009,
			"is_binary": false
		},
		"src/pkg/reflect/makefunc.go": {
			"status": "A",
			"num_chunks": 1,
			"no_base_file": false,
			"property_changes": "",
			"num_added": 147,
			"num_removed": 0,
			"id": 10008,
			"is_binary": false
		},
		"src/pkg/reflect/asm_arm.s": {
			"status": "A",
			"num_chunks": 1,
			"no_base_file": false,
			"property_changes": "",
			"num_added": 17,
			"num_removed": 0,
			"id": 10006,
			"is_binary": false
		}
	},
	"url": null,
	"created": "2012-09-23 17:51:44.922980",
	"owner": "rsc",
	"num_comments": 0,
	"patchset": 13013,
	"owner_email": "rsc@golang.org",
	"issue": 6554067,
	"message": "diff -r 29cff1e8de4e https://code.google.com/p/go/",
	"modified": "2012-09-23 17:51:44.923340"
}