{
	"files": {
		"src/pkg/crypto/x509/block_decrypt.go": {
			"status": "A",
			"num_chunks": 1,
			"no_base_file": false,
			"property_changes": "",
			"num_added": 104,
			"num_removed": 0,
			"id": 2001,
			"is_binary": false
		},
		"src/pkg/crypto/x509/block_decrypt_test.go": {
			"status": "A",
			"num_chunks": 1,
			"no_base_file": false,
			"property_changes": "",
			"num_added": 110,
			"num_removed": 0,
			"id": 2002,
			"is_binary": false
		}
	},
	"url": null,
	"created": "2012-09-22 00:01:27.597510",
	"owner": "zeebo",
	"num_comments": 0,
	"patchset": 1002,
	"owner_email": "jeff@spacemonkey.com",
	"issue": 6555052,
	"message": "diff -r 24d74bd32d81 https://code.google.com/p/go",
	"modified": "2012-09-22 00:01:27.598070"
}