{
	"files": {
		"src/pkg/net/textproto/reader_test.go": {
			"status": "M",
			"num_chunks": 1,
			"no_base_file": false,
			"property_changes": "",
			"num_added": 23,
			"num_removed": 0,
			"id": 5002,
			"is_binary": false
		},
		"src/pkg/net/textproto/reader.go": {
			"status": "M",
			"num_chunks": 2,
			"no_base_file": false,
			"property_changes": "",
			"num_added": 11,
			"num_removed": 2,
			"id": 5001,
			"is_binary": false
		}
	},
	"url": null,
	"created": "2012-02-21 22:55:48.172839",
	"owner": "bradfitz",
	"num_comments": 1,
	"patchset": 4001,
	"owner_email": "bradfitz@golang.org",
	"issue": 5690059,
	"message": "diff -r d83ad2b46bee https://go.googlecode.com/hg/",
	"modified": "2012-02-21 23:44:24.624491"
}