{
	"files": {
		"src/cmd/yacc/doc.go": {
			"status": "M",
			"num_chunks": 1,
			"no_base_file": false,
			"property_changes": "",
			"num_added": 7,
			"num_removed": 2,
			"id": 3015,
			"is_binary": false
		},
		"src/cmd/prof/doc.go": {
			"status": "M",
			"num_chunks": 1,
			"no_base_file": false,
			"property_changes": "",
			"num_added": 3,
			"num_removed": 1,
			"id": 3014,
			"is_binary": false
		},
		"src/cmd/8c/doc.go": {
			"status": "M",
			"num_chunks": 1,
			"no_base_file": false,
			"property_changes": "",
			"num_added": 3,
			"num_removed": 1,
			"id": 3006,
			"is_binary": false
		},
		"src/cmd/cgo/doc.go": {
			"status": "M",
			"num_chunks": 1,
			"no_base_file": false,
			"property_changes": "",
			"num_added": 3,
			"num_removed": 1,
			"id": 3007,
			"is_binary": false
		},
		"src/cmd/5c/doc.go": {
			"status": "M",
			"num_chunks": 1,
			"no_base_file": false,
			"property_changes": "",
			"num_added": 3,
			"num_removed": 1,
			"id": 3002,
			"is_binary": false
		},
		"src/cmd/6a/doc.go": {
			"status": "M",
			"num_chunks": 1,
			"no_base_file": false,
			"property_changes": "",
			"num_added": 3,
			"num_removed": 1,
			"id": 3003,
			"is_binary": false
		},
		"src/cmd/ld/doc.go": {
			"status": "M",
			"num_chunks": 2,
			"no_base_file": false,
			"property_changes": "",
			"num_added": 32,
			"num_removed": 30,
			"id": 3011,
			"is_binary": false
		},
		"src/cmd/gc/doc.go": {
			"status": "M",
			"num_chunks": 1,
			"no_base_file": false,
			"property_changes": "",
			"num_added": 3,
			"num_removed": 2,
			"id": 3009,
			"is_binary": false
		},
		"src/cmd/8a/doc.go": {
			"status": "M",
			"num_chunks": 1,
			"no_base_file": false,
			"property_changes": "",
			"num_added": 3,
			"num_removed": 1,
			"id": 3005,
			"is_binary": false
		},
		"src/cmd/5a/doc.go": {
			"status": "M",
			"num_chunks": 1,
			"no_base_file": false,
			"property_changes": "",
			"num_added": 3,
			"num_removed": 1,
			"id": 3001,
			"is_binary": false
		},
		"src/cmd/6c/doc.go": {
			"status": "M",
			"num_chunks": 1,
			"no_base_file": false,
			"property_changes": "",
			"num_added": 3,
			"num_removed": 1,
			"id": 3004,
			"is_binary": false
		},
		"src/cmd/nm/doc.go": {
			"status": "M",
			"num_chunks": 1,
			"no_base_file": false,
			"property_changes": "",
			"num_added": 3,
			"num_removed": 1,
			"id": 3012,
			"is_binary": false
		},
		"src/cmd/go/doc.go": {
			"status": "M",
			"num_chunks": 1,
			"no_base_file": false,
			"property_changes": "",
			"num_added": 3,
			"num_removed": 1,
			"id": 3010,
			"is_binary": false
		},
		"src/cmd/pack/doc.go": {
			"status": "M",
			"num_chunks": 2,
			"no_base_file": false,
			"property_changes": "",
			"num_added": 15,
			"num_removed": 8,
			"id": 3013,
			"is_binary": false
		},
		"src/cmd/cov/doc.go": {
			"status": "M",
			"num_chunks": 1,
			"no_base_file": false,
			"property_changes": "",
			"num_added": 3,
			"num_removed": 1,
			"id": 3008,
			"is_binary": false
		}
	},
	"url": null,
	"created": "2012-02-27 13:00:50.929648",
	"owner": "rcostu",
	"num_comments": 0,
	"patchset": 2001,
	"owner_email": "rcostu@gmail.com",
	"issue": 5695074,
	"message": "diff -r bf0768b1dece https://go.googlecode.com/hg/",
	"modified": "2012-02-27 13:00:50.929928"
}