{
	"files": {
		"src/pkg/exp/template/html/css.go": {
			"status": "M",
			"num_chunks": 4,
			"no_base_file": false,
			"property_changes": "",
			"num_added": 9,
			"num_removed": 5,
			"id": 31008,
			"is_binary": false
		},
		"src/pkg/exp/template/html/doc.go": {
			"status": "M",
			"num_chunks": 3,
			"no_base_file": false,
			"property_changes": "",
			"num_added": 4,
			"num_removed": 35,
			"id": 31009,
			"is_binary": false
		},
		"src/pkg/exp/template/html/html_test.go": {
			"status": "M",
			"num_chunks": 4,
			"no_base_file": false,
			"property_changes": "",
			"num_added": 39,
			"num_removed": 3,
			"id": 31013,
			"is_binary": false
		},
		"src/pkg/exp/template/html/js.go": {
			"status": "M",
			"num_chunks": 5,
			"no_base_file": false,
			"property_changes": "",
			"num_added": 40,
			"num_removed": 14,
			"id": 31014,
			"is_binary": false
		},
		"src/pkg/exp/template/html/content_test.go": {
			"status": "A",
			"num_chunks": 1,
			"no_base_file": false,
			"property_changes": "",
			"num_added": 196,
			"num_removed": 0,
			"id": 31007,
			"is_binary": false
		},
		"src/pkg/exp/template/html/escape_test.go": {
			"status": "M",
			"num_chunks": 4,
			"no_base_file": false,
			"property_changes": "",
			"num_added": 41,
			"num_removed": 2,
			"id": 31011,
			"is_binary": false
		},
		"src/pkg/exp/template/html/html.go": {
			"status": "M",
			"num_chunks": 2,
			"no_base_file": false,
			"property_changes": "",
			"num_added": 179,
			"num_removed": 73,
			"id": 31012,
			"is_binary": false
		},
		"src/pkg/exp/template/html/Makefile": {
			"status": "M",
			"num_chunks": 1,
			"no_base_file": false,
			"property_changes": "",
			"num_added": 1,
			"num_removed": 0,
			"id": 31005,
			"is_binary": false
		},
		"src/pkg/exp/template/html/content.go": {
			"status": "A",
			"num_chunks": 1,
			"no_base_file": false,
			"property_changes": "",
			"num_added": 83,
			"num_removed": 0,
			"id": 31006,
			"is_binary": false
		},
		"src/pkg/exp/template/html/url.go": {
			"status": "M",
			"num_chunks": 3,
			"no_base_file": false,
			"property_changes": "",
			"num_added": 9,
			"num_removed": 3,
			"id": 31015,
			"is_binary": false
		},
		"src/pkg/exp/template/html/escape.go": {
			"status": "M",
			"num_chunks": 8,
			"no_base_file": false,
			"property_changes": "",
			"num_added": 38,
			"num_removed": 9,
			"id": 31010,
			"is_binary": false
		}
	},
	"url": null,
	"created": "2011-09-15 15:51:51.479503",
	"owner": "MikeSamuel",
	"num_comments": 0,
	"patchset": 20011,
	"owner_email": "mikesamuel@gmail.com",
	"issue": 4962067,
	"message": "diff -r d21944c38c39 https://go.googlecode.com/hg/",
	"modified": "2011-09-15 15:51:51.479792"
}