{
	"files": {
		"src/pkg/time/format.go": {
			"status": "M",
			"num_chunks": 3,
			"no_base_file": false,
			"property_changes": "",
			"num_added": 16,
			"num_removed": 10,
			"id": 3001,
			"is_binary": false
		}
	},
	"url": null,
	"created": "2013-04-08 17:33:23.409650",
	"owner": "bradfitz",
	"num_comments": 0,
	"patchset": 2001,
	"owner_email": "bradfitz@golang.org",
	"issue": 8478044,
	"message": "diff -r 1d49ee511d95 https://go.googlecode.com/hg/",
	"modified": "2013-04-08 17:33:23.410080"
}