{
	"files": {
		"CONTRIBUTORS": {
			"status": "M",
			"num_chunks": 1,
			"no_base_file": false,
			"property_changes": "",
			"num_added": 1,
			"num_removed": 0,
			"id": 4002,
			"is_binary": false
		},
		"AUTHORS": {
			"status": "M",
			"num_chunks": 1,
			"no_base_file": false,
			"property_changes": "",
			"num_added": 1,
			"num_removed": 0,
			"id": 4001,
			"is_binary": false
		}
	},
	"url": null,
	"created": "2013-06-24 03:27:12.470880",
	"owner": "adg",
	"num_comments": 0,
	"patchset": 3001,
	"owner_email": "adg@golang.org",
	"issue": 10482043,
	"message": "diff -r 5b2b5f8d89b0 https://code.google.com/p/go",
	"modified": "2013-06-24 03:27:12.471470"
}