{
	"files": {
		"test/bench/go/asop_test.go": {
			"status": "A",
			"num_chunks": 1,
			"no_base_file": false,
			"property_changes": "",
			"num_added": 73,
			"num_removed": 0,
			"id": 10002,
			"is_binary": false
		},
		"test/bench/go/divmul_test.go": {
			"status": "M",
			"num_chunks": 4,
			"no_base_file": false,
			"property_changes": "",
			"num_added": 116,
			"num_removed": 2,
			"id": 10003,
			"is_binary": false
		},
		"test/bench/go/doc.go": {
			"status": "A",
			"num_chunks": 1,
			"no_base_file": false,
			"property_changes": "",
			"num_added": 6,
			"num_removed": 0,
			"id": 10004,
			"is_binary": false
		}
	},
	"url": null,
	"created": "2012-11-08 01:15:29.114940",
	"owner": "dfc",
	"num_comments": 2,
	"patchset": 5005,
	"owner_email": "dave@cheney.net",
	"issue": 6819087,
	"message": "diff -r a53601cd4e63 https://code.google.com/p/go",
	"modified": "2012-11-11 23:48:02.326510"
}