{
	"files": {
		"src/pkg/path/filepath/path_test.go": {
			"status": "M",
			"num_chunks": 5,
			"no_base_file": false,
			"property_changes": "",
			"num_added": 65,
			"num_removed": 0,
			"id": 9012,
			"is_binary": false
		},
		"src/pkg/path/filepath/path_unix.go": {
			"status": "M",
			"num_chunks": 1,
			"no_base_file": false,
			"property_changes": "",
			"num_added": 5,
			"num_removed": 0,
			"id": 9013,
			"is_binary": false
		},
		"src/pkg/path/filepath/path_plan9.go": {
			"status": "M",
			"num_chunks": 1,
			"no_base_file": false,
			"property_changes": "",
			"num_added": 5,
			"num_removed": 0,
			"id": 9011,
			"is_binary": false
		},
		"src/pkg/path/filepath/path.go": {
			"status": "M",
			"num_chunks": 2,
			"no_base_file": false,
			"property_changes": "",
			"num_added": 6,
			"num_removed": 2,
			"id": 9010,
			"is_binary": false
		},
		"src/pkg/path/filepath/path_windows.go": {
			"status": "M",
			"num_chunks": 3,
			"no_base_file": false,
			"property_changes": "",
			"num_added": 40,
			"num_removed": 1,
			"id": 9014,
			"is_binary": false
		}
	},
	"url": null,
	"created": "2011-09-08 08:17:14.149614",
	"owner": "mattn",
	"num_comments": 0,
	"patchset": 24006,
	"owner_email": "mattn.jp@gmail.com",
	"issue": 4950051,
	"message": "diff -r d084dfee7dd3 http://go.googlecode.com/hg/",
	"modified": "2011-09-08 08:17:14.149910"
}