{
	"files": {
		"misc/backport/patches/text-template-parse-lex-test.diff": {
			"status": "A",
			"num_chunks": 1,
			"no_base_file": false,
			"property_changes": "",
			"num_added": 13,
			"num_removed": 0,
			"id": 5004,
			"is_binary": false
		},
		"misc/backport/backport": {
			"status": "A",
			"num_chunks": 1,
			"no_base_file": false,
			"property_changes": "",
			"num_added": 50,
			"num_removed": 0,
			"id": 5001,
			"is_binary": false
		},
		"misc/backport/go103": {
			"status": "A",
			"num_chunks": 1,
			"no_base_file": false,
			"property_changes": "",
			"num_added": 162,
			"num_removed": 0,
			"id": 5002,
			"is_binary": false
		},
		"misc/backport/graftedit": {
			"status": "A",
			"num_chunks": 1,
			"no_base_file": false,
			"property_changes": "",
			"num_added": 16,
			"num_removed": 0,
			"id": 5003,
			"is_binary": false
		}
	},
	"url": null,
	"created": "2012-09-11 05:35:23.848130",
	"owner": "adg",
	"num_comments": 0,
	"patchset": 1002,
	"owner_email": "adg@golang.org",
	"issue": 6499087,
	"message": "diff -r 50457a54c26c https://go.googlecode.com/hg",
	"modified": "2012-09-11 05:35:23.851320"
}