{
	"files": {
		"src/pkg/runtime/proc.c": {
			"status": "M",
			"num_chunks": 2,
			"no_base_file": false,
			"property_changes": "",
			"num_added": 2,
			"num_removed": 13,
			"id": 1001,
			"is_binary": false
		}
	},
	"url": null,
	"created": "2011-10-05 19:18:05.025513",
	"owner": "dvyukov",
	"num_comments": 0,
	"patchset": 4,
	"owner_email": "dvyukov@google.com",
	"issue": 5191044,
	"message": "diff -r a5126bbf1e47 https://go.googlecode.com/hg/",
	"modified": "2011-10-05 19:18:05.025933"
}