{
	"files": {
		"src/pkg/archive/zip/reader.go": {
			"status": "M",
			"num_chunks": 2,
			"no_base_file": false,
			"property_changes": "",
			"num_added": 6,
			"num_removed": 1,
			"id": 5001,
			"is_binary": false
		},
		"src/pkg/archive/zip/reader_test.go": {
			"status": "M",
			"num_chunks": 2,
			"no_base_file": false,
			"property_changes": "",
			"num_added": 19,
			"num_removed": 1,
			"id": 5002,
			"is_binary": false
		},
		"src/pkg/archive/zip/testdata/test-trailing-junk.zip": {
			"status": "A",
			"num_chunks": 0,
			"no_base_file": false,
			"property_changes": "",
			"num_added": -1,
			"num_removed": -1,
			"id": 5003,
			"is_binary": true
		}
	},
	"url": null,
	"created": "2013-04-08 05:37:58.594840",
	"owner": "adg",
	"num_comments": 0,
	"patchset": 4001,
	"owner_email": "adg@golang.org",
	"issue": 8504044,
	"message": "diff -r b7fb7733b29b https://code.google.com/p/go",
	"modified": "2013-04-08 05:37:58.595200"
}