{
	"files": {
		"src/pkg/net/textproto/textproto.go": {
			"status": "M",
			"num_chunks": 1,
			"no_base_file": false,
			"property_changes": "",
			"num_added": 5,
			"num_removed": 0,
			"id": 3002,
			"is_binary": false
		},
		"src/pkg/net/textproto/reader.go": {
			"status": "M",
			"num_chunks": 2,
			"no_base_file": false,
			"property_changes": "",
			"num_added": 11,
			"num_removed": 1,
			"id": 3001,
			"is_binary": false
		}
	},
	"url": null,
	"created": "2013-02-12 23:18:27.556930",
	"owner": "dfc",
	"num_comments": 1,
	"patchset": 2001,
	"owner_email": "dave@cheney.net",
	"issue": 7300098,
	"message": "diff -r 86c70475d48f https://code.google.com/p/go",
	"modified": "2013-02-12 23:37:15.743030"
}