{
	"files": {
		"goplay/edit.html": {
			"status": "M",
			"num_chunks": 2,
			"no_base_file": false,
			"property_changes": "",
			"num_added": 9,
			"num_removed": 2,
			"id": 12002,
			"is_binary": false
		},
		"static/style.css": {
			"status": "M",
			"num_chunks": 3,
			"no_base_file": false,
			"property_changes": "",
			"num_added": 21,
			"num_removed": 2,
			"id": 12003,
			"is_binary": false
		},
		"goplay/edit.go": {
			"status": "M",
			"num_chunks": 2,
			"no_base_file": false,
			"property_changes": "",
			"num_added": 7,
			"num_removed": 1,
			"id": 12001,
			"is_binary": false
		}
	},
	"url": null,
	"created": "2012-03-15 07:08:24.991523",
	"owner": "adg",
	"num_comments": 0,
	"patchset": 2005,
	"owner_email": "adg@golang.org",
	"issue": 5821045,
	"message": "diff -r ec6f67c45b69 https://code.google.com/p/go-playground",
	"modified": "2012-03-15 07:08:24.991979"
}