{
	"files": {
		"src/pkg/database/sql/sql_test.go": {
			"status": "M",
			"num_chunks": 1,
			"no_base_file": false,
			"property_changes": "",
			"num_added": 28,
			"num_removed": 0,
			"id": 8003,
			"is_binary": false
		},
		"src/pkg/database/sql/convert.go": {
			"status": "M",
			"num_chunks": 2,
			"no_base_file": false,
			"property_changes": "",
			"num_added": 9,
			"num_removed": 0,
			"id": 8001,
			"is_binary": false
		},
		"src/pkg/database/sql/sql.go": {
			"status": "M",
			"num_chunks": 2,
			"no_base_file": false,
			"property_changes": "",
			"num_added": 6,
			"num_removed": 7,
			"id": 8002,
			"is_binary": false
		}
	},
	"url": null,
	"created": "2012-01-26 22:29:25.783479",
	"owner": "coopernurse",
	"num_comments": 1,
	"patchset": 7001,
	"owner_email": "jamespcooper@gmail.com",
	"issue": 5577054,
	"message": "diff -r b78d387bd5c7 https://go.googlecode.com/hg/",
	"modified": "2012-01-26 22:36:59.550842"
}