{
	"files": {
		"src/pkg/net/url/url.go": {
			"status": "M",
			"num_chunks": 1,
			"no_base_file": false,
			"property_changes": "",
			"num_added": 4,
			"num_removed": 0,
			"id": 18002,
			"is_binary": false
		},
		"src/pkg/net/url/url_test.go": {
			"status": "M",
			"num_chunks": 1,
			"no_base_file": false,
			"property_changes": "",
			"num_added": 18,
			"num_removed": 0,
			"id": 18003,
			"is_binary": false
		},
		"src/pkg/net/http/requestwrite_test.go": {
			"status": "M",
			"num_chunks": 1,
			"no_base_file": false,
			"property_changes": "",
			"num_added": 38,
			"num_removed": 0,
			"id": 18001,
			"is_binary": false
		}
	},
	"url": null,
	"created": "2013-02-21 20:01:43.319630",
	"owner": "bradfitz",
	"num_comments": 0,
	"patchset": 12002,
	"owner_email": "bradfitz@golang.org",
	"issue": 7369045,
	"message": "diff -r dbf506e7a2fe https://go.googlecode.com/hg/",
	"modified": "2013-02-21 20:01:43.319990"
}