{
	"files": {
		"src/pkg/encoding/xml/read.go": {
			"status": "M",
			"num_chunks": 12,
			"no_base_file": false,
			"property_changes": "",
			"num_added": 65,
			"num_removed": 4,
			"id": 20009,
			"is_binary": false
		},
		"src/pkg/encoding/xml/read_test.go": {
			"status": "M",
			"num_chunks": 2,
			"no_base_file": false,
			"property_changes": "",
			"num_added": 274,
			"num_removed": 0,
			"id": 20010,
			"is_binary": false
		},
		"src/pkg/encoding/xml/xml.go": {
			"status": "M",
			"num_chunks": 1,
			"no_base_file": false,
			"property_changes": "",
			"num_added": 4,
			"num_removed": 0,
			"id": 20012,
			"is_binary": false
		},
		"src/pkg/encoding/xml/typeinfo.go": {
			"status": "M",
			"num_chunks": 4,
			"no_base_file": false,
			"property_changes": "",
			"num_added": 23,
			"num_removed": 4,
			"id": 20011,
			"is_binary": false
		}
	},
	"url": null,
	"created": "2013-03-01 00:14:07.762990",
	"owner": "kortschak",
	"num_comments": 0,
	"patchset": 19002,
	"owner_email": "dan.kortschak@adelaide.edu.au",
	"issue": 7379049,
	"message": "diff -r 233d3634332f https://go.googlecode.com/hg/",
	"modified": "2013-03-01 00:14:07.763290"
}