{
	"files": {
		"src/pkg/os/stat_openbsd.go": {
			"status": "M",
			"num_chunks": 1,
			"no_base_file": false,
			"property_changes": "",
			"num_added": 3,
			"num_removed": 0,
			"id": 2006,
			"is_binary": false
		},
		"src/pkg/os/stat_darwin.go": {
			"status": "M",
			"num_chunks": 1,
			"no_base_file": false,
			"property_changes": "",
			"num_added": 3,
			"num_removed": 0,
			"id": 2002,
			"is_binary": false
		},
		"src/pkg/os/stat_netbsd.go": {
			"status": "M",
			"num_chunks": 1,
			"no_base_file": false,
			"property_changes": "",
			"num_added": 3,
			"num_removed": 0,
			"id": 2005,
			"is_binary": false
		},
		"src/pkg/os/stat_freebsd.go": {
			"status": "M",
			"num_chunks": 1,
			"no_base_file": false,
			"property_changes": "",
			"num_added": 3,
			"num_removed": 0,
			"id": 2003,
			"is_binary": false
		},
		"src/pkg/os/stat_linux.go": {
			"status": "M",
			"num_chunks": 1,
			"no_base_file": false,
			"property_changes": "",
			"num_added": 3,
			"num_removed": 0,
			"id": 2004,
			"is_binary": false
		},
		"src/pkg/os/types.go": {
			"status": "M",
			"num_chunks": 1,
			"no_base_file": false,
			"property_changes": "",
			"num_added": 2,
			"num_removed": 1,
			"id": 2007,
			"is_binary": false
		}
	},
	"url": null,
	"created": "2012-01-15 02:55:08.168002",
	"owner": "eds",
	"num_comments": 0,
	"patchset": 2001,
	"owner_email": "chickencha@gmail.com",
	"issue": 5539063,
	"message": "diff -r 8c6f3122826c https://go.googlecode.com/hg/",
	"modified": "2012-01-15 02:55:08.168352"
}