{
	"files": {
		"proto/text_parser_test.go": {
			"status": "M",
			"num_chunks": 1,
			"no_base_file": false,
			"property_changes": "",
			"num_added": 16,
			"num_removed": 0,
			"id": 9003,
			"is_binary": false
		},
		"proto/text_parser.go": {
			"status": "M",
			"num_chunks": 3,
			"no_base_file": false,
			"property_changes": "",
			"num_added": 4,
			"num_removed": 4,
			"id": 9002,
			"is_binary": false
		}
	},
	"url": null,
	"created": "2012-06-15 14:59:02.270592",
	"owner": "dsymonds",
	"num_comments": 0,
	"patchset": 4003,
	"owner_email": "dsymonds@golang.org",
	"issue": 6301088,
	"message": "diff -r 6a3d154261b5 https://code.google.com/p/goprotobuf",
	"modified": "2012-06-15 14:59:02.270814"
}