{
	"files": {
		"src/pkg/runtime/memmove_arm.s": {
			"status": "M",
			"num_chunks": 9,
			"no_base_file": false,
			"property_changes": "",
			"num_added": 48,
			"num_removed": 44,
			"id": 6,
			"is_binary": false
		}
	},
	"url": null,
	"created": "2012-06-17 22:53:41.328204",
	"owner": "dfc",
	"num_comments": 2,
	"patchset": 2004,
	"owner_email": "dave@cheney.net",
	"issue": 6305100,
	"message": "diff -r 5e3661048f2e https://code.google.com/p/go",
	"modified": "2012-06-19 20:52:01.757726"
}