{
	"files": {
		"src/pkg/net/iprawsock_posix.go": {
			"status": "M",
			"num_chunks": 3,
			"no_base_file": false,
			"property_changes": "",
			"num_added": 7,
			"num_removed": 4,
			"id": 52001,
			"is_binary": false
		},
		"src/pkg/net/unixsock_posix.go": {
			"status": "M",
			"num_chunks": 3,
			"no_base_file": false,
			"property_changes": "",
			"num_added": 8,
			"num_removed": 9,
			"id": 52008,
			"is_binary": false
		},
		"src/pkg/net/sock_unix.go": {
			"status": "M",
			"num_chunks": 1,
			"no_base_file": false,
			"property_changes": "",
			"num_added": 11,
			"num_removed": 11,
			"id": 52004,
			"is_binary": false
		},
		"src/pkg/net/sock_posix.go": {
			"status": "M",
			"num_chunks": 4,
			"no_base_file": false,
			"property_changes": "",
			"num_added": 41,
			"num_removed": 17,
			"id": 52003,
			"is_binary": false
		},
		"src/pkg/net/ipsock_posix.go": {
			"status": "M",
			"num_chunks": 1,
			"no_base_file": false,
			"property_changes": "",
			"num_added": 1,
			"num_removed": 12,
			"id": 52002,
			"is_binary": false
		},
		"src/pkg/net/tcpsock_posix.go": {
			"status": "M",
			"num_chunks": 4,
			"no_base_file": false,
			"property_changes": "",
			"num_added": 8,
			"num_removed": 5,
			"id": 52006,
			"is_binary": false
		},
		"src/pkg/net/sock_windows.go": {
			"status": "M",
			"num_chunks": 1,
			"no_base_file": false,
			"property_changes": "",
			"num_added": 11,
			"num_removed": 11,
			"id": 52005,
			"is_binary": false
		},
		"src/pkg/net/udpsock_posix.go": {
			"status": "M",
			"num_chunks": 4,
			"no_base_file": false,
			"property_changes": "",
			"num_added": 8,
			"num_removed": 5,
			"id": 52007,
			"is_binary": false
		}
	},
	"url": null,
	"created": "2013-08-03 04:32:11.272810",
	"owner": "mikio",
	"num_comments": 0,
	"patchset": 51001,
	"owner_email": "mikioh.mikioh@gmail.com",
	"issue": 12010043,
	"message": "diff -r 7c06f390d1ad https://code.google.com/p/go",
	"modified": "2013-08-03 04:32:11.273440"
}