{
	"files": {
		"go/types/issues_test.go": {
			"status": "M",
			"num_chunks": 1,
			"no_base_file": false,
			"property_changes": "",
			"num_added": 22,
			"num_removed": 0,
			"id": 9002,
			"is_binary": false
		},
		"go/types/gcimporter.go": {
			"status": "M",
			"num_chunks": 4,
			"no_base_file": false,
			"property_changes": "",
			"num_added": 10,
			"num_removed": 15,
			"id": 9001,
			"is_binary": false
		}
	},
	"url": null,
	"created": "2013-07-29 20:01:51.898330",
	"owner": "gri",
	"num_comments": 4,
	"patchset": 8001,
	"owner_email": "gri@golang.org",
	"issue": 12048043,
	"message": "diff -r b24277f5d911 https://code.google.com/p/go.tools",
	"modified": "2013-07-29 20:21:12.045600"
}