{
	"files": {
		"src/pkg/runtime/thread_netbsd.c": {
			"status": "M",
			"num_chunks": 7,
			"no_base_file": false,
			"property_changes": "",
			"num_added": 53,
			"num_removed": 21,
			"id": 12004,
			"is_binary": false
		},
		"src/pkg/runtime/signal_netbsd_amd64.c": {
			"status": "M",
			"num_chunks": 2,
			"no_base_file": false,
			"property_changes": "",
			"num_added": 12,
			"num_removed": 0,
			"id": 12002,
			"is_binary": false
		},
		"src/pkg/runtime/os_netbsd.h": {
			"status": "M",
			"num_chunks": 1,
			"no_base_file": false,
			"property_changes": "",
			"num_added": 1,
			"num_removed": 1,
			"id": 12001,
			"is_binary": false
		},
		"src/pkg/runtime/sys_netbsd_amd64.s": {
			"status": "M",
			"num_chunks": 3,
			"no_base_file": false,
			"property_changes": "",
			"num_added": 22,
			"num_removed": 39,
			"id": 12003,
			"is_binary": false
		}
	},
	"url": null,
	"created": "2012-05-23 11:29:07.638527",
	"owner": "jsing",
	"num_comments": 1,
	"patchset": 7002,
	"owner_email": "jsing@google.com",
	"issue": 6222044,
	"message": "diff -r ff109fe72249 https://go.googlecode.com/hg/",
	"modified": "2012-05-23 17:54:58.963218"
}