{
	"files": {
		"misc/dashboard/app/build/handler.go": {
			"status": "M",
			"num_chunks": 2,
			"no_base_file": false,
			"property_changes": "",
			"num_added": 13,
			"num_removed": 0,
			"id": 5001,
			"is_binary": false
		}
	},
	"url": null,
	"created": "2012-02-03 03:03:41.142035",
	"owner": "adg",
	"num_comments": 0,
	"patchset": 4001,
	"owner_email": "adg@golang.org",
	"issue": 5608044,
	"message": "diff -r a3a707ba21f5 https://go.googlecode.com/hg",
	"modified": "2012-02-03 03:03:41.142340"
}