{
	"files": {
		"ssa/util.go": {
			"status": "M",
			"num_chunks": 1,
			"no_base_file": false,
			"property_changes": "",
			"num_added": 0,
			"num_removed": 17,
			"id": 3006,
			"is_binary": false
		},
		"ssa/typeinfo.go": {
			"status": "M",
			"num_chunks": 2,
			"no_base_file": false,
			"property_changes": "",
			"num_added": 6,
			"num_removed": 4,
			"id": 3005,
			"is_binary": false
		},
		"ssa/builder.go": {
			"status": "M",
			"num_chunks": 3,
			"no_base_file": false,
			"property_changes": "",
			"num_added": 4,
			"num_removed": 7,
			"id": 3004,
			"is_binary": false
		}
	},
	"url": null,
	"created": "2013-05-30 15:16:02.010370",
	"owner": "adonovan",
	"num_comments": 0,
	"patchset": 2002,
	"owner_email": "adonovan@google.com",
	"issue": 9740052,
	"message": "diff -r ced2d1cfc206 https://code.google.com/p/go.tools",
	"modified": "2013-05-30 15:16:02.010660"
}